[{
  "_id": {
    "$oid": "602eadde20bd321f4cf04823"
  },
  "hats": [
    {
      "title": "Bucket Hat",
      "cost": "109",
      "src": "Hats\\bucket-hat-for-women.jpg",
      "ItemId": "hatw1",
      "Details": {},
      "pindex": -1
    },
    {
      "title": "Maroon Fedora",
      "cost": "129",
      "src": "Hats\\fedora.jpg",
      "ItemId": "hatw2",
      "Details": {},
      "pindex": -1.4
    },
    {
      "title": "Nike Head Tie",
      "cost": "69",
      "src": "Hats\\Nike women head tie.jpg",
      "ItemId": "hatw3",
      "Details": {},
      "pindex": -2.4
    },
    {
      "title": "Cowboy Hat for Women",
      "cost": "149",
      "src": "Hats\\Womens-Cowboy-hat.jpg",
      "ItemId": "hatw4",
      "Details": {},
      "pindex": -0.5
    }
  ]
},{
  "_id": {
    "$oid": "603beeb28e2bbb0f04cc3ea2"
  },
  "jackets": [
    {
      "title": "Brown Chesterfield Coat",
      "cost": "3849",
      "src": "Jackets\\brown-chesterfield-coat.jpeg",
      "ItemId": "jacketw1",
      "Details": {},
      "pindex": -3.4
    },
    {
      "title": "Burberry Cotton Trench Coat",
      "cost": "5499",
      "src": "Jackets\\burberry-antique-cotton-trench-coat.jpeg",
      "ItemId": "jacketw2",
      "Details": {},
      "pindex": 3.4
    },
    {
      "title": "Camel color Duffle Coat",
      "cost": "4699",
      "src": "Jackets\\camel-detachable-fur-duffle-coat.jpeg",
      "ItemId": "jacketw3",
      "Details": {},
      "pindex": -2.8
    },
    {
      "title": "Fur Coat",
      "cost": "5899",
      "src": "Jackets\\fur-coat.jpg",
      "ItemId": "jacketw4",
      "Details": {},
      "pindex": 1.4
    },
    {
      "title": "White Trench Coat",
      "cost": "5999",
      "src": "Jackets\\ivory-flared-trench-coat.jpeg",
      "ItemId": "jacketw5",
      "Details": {},
      "pindex": -3.9
    },
    {
      "title": "Stylish Mackintosh",
      "cost": "3999",
      "src": "Jackets\\Mackintosh.jpg",
      "ItemId": "jacketw6",
      "Details": {},
      "pindex": -2.9
    },
    {
      "title": "Nike Black&White Windrunner",
      "cost": "3349",
      "src": "Jackets\\nike-womens-sports-black-and-white-windrunner-puffer.jpg",
      "ItemId": "jacketw7",
      "Details": {},
      "pindex": -1.8
    },
    {
      "title": "Pea Coat",
      "cost": "4549",
      "src": "Jackets\\Pea-coat.jpg",
      "ItemId": "jacketw8",
      "Details": {},
      "pindex": 0.9
    },
    {
      "title": "Windbreaker for winters",
      "cost": "3049",
      "src": "Jackets\\Windbreaker-Jacket.jpg",
      "ItemId": "jacketw9",
      "Details": {},
      "pindex": -4.4
    },
    {
      "title": "Jacket for winters",
      "cost": "2999",
      "src": "Jackets\\Winter Jacket.jpg",
      "ItemId": "jacketw10",
      "Details": {},
      "pindex": 2.5
    },
    {
      "title": "High Neck long sleeve pullover long sweater",
      "cost": "1999",
      "src": "Jackets\\High Neck long sleeve pullover long sweater.jpg",
      "ItemId": "jacketw11",
      "Details": {},
      "pindex": 2.9
    }
  ]
},{
  "_id": {
    "$oid": "603bf1068e2bbb0f04cc3ea3"
  },
  "tops": [
    {
      "title": "Blue White Crop Top",
      "cost": 849,
      "src": "Tops\\women crop tops.jpg",
      "ItemId": "topw1",
      "Details": {},
      "pindex": 0.7
    },
    {
      "cost": 399,
      "title": "White top for women",
      "src": "Tops\\best-seller-3.jpg",
      "ItemId": "topw2",
      "Details": {},
      "pindex": 0.1
    },
    {
      "cost": 699,
      "title": "Women Trouser",
      "src": "Tops\\best-seller-4.jpeg",
      "ItemId": "topw3",
      "Details": {},
      "pindex": -1.8
    },
    {
      "title": "Stylish windbreaker for women",
      "src": "Tops\\best-seller-9.jpg",
      "cost": 599,
      "ItemId": "topw4",
      "Details": {},
      "pindex": 5
    },
    {
      "title": "Stylish cutwork Blouse",
      "cost": "599",
      "ItemId": "topw5",
      "src": "Tops\\best-seller-12.jpg",
      "Details": {},
      "pindex": 3.3
    }
  ]
}]